StatsViz/__init__.py
StatsViz/__main__.py
StatsViz/calculation.py
StatsViz/graphing.py
StatsViz/interfaceCommon.py
StatsViz/interfaceHist.py
StatsViz/interfaceInterval.py
StatsViz/interfaceRoot.py
StatsViz/interfaceScatter.py
StatsViz/rw.py
statsviz-1.2.2.dist-info/LICENSE
statsviz-1.2.2.dist-info/METADATA
statsviz-1.2.2.dist-info/WHEEL
statsviz-1.2.2.dist-info/top_level.txt
statsviz-1.2.2.dist-info/RECORD
