Metadata-Version: 2.1
Name: statsviz
Version: 1.2.2
Summary: A package that provides a gui to plot graphs from CSV files
Home-page: https://github.com/j0371/StatsViz
Author: Marcus Higgins
Author-email: halo2305@gmail.com
License: UNKNOWN
Platform: UNKNOWN
Classifier: Programming Language :: Python :: 3
Classifier: License :: OSI Approved :: MIT License
Classifier: Operating System :: OS Independent
Requires-Dist: matplotlib
Requires-Dist: scipy
Requires-Dist: natsort
